pypums/__init__.py
pypums/__main__.py
pypums/cli.py
pypums/constants.py
pypums/surveys.py
pypums/utils.py
pypums-0.1.dist-info/LICENSE
pypums-0.1.dist-info/METADATA
pypums-0.1.dist-info/WHEEL
pypums-0.1.dist-info/entry_points.txt
pypums-0.1.dist-info/top_level.txt
pypums-0.1.dist-info/RECORD
