Metadata-Version: 2.1
Name: pypums
Version: 0.1
Summary: Download Public Use Micro Sample (PUMS) data files from the US Census Bureau's FTP server.
Home-page: https://github.com/chekos/pypums
Author: Sergio Sanchez
License: Apache License, Version 2.0
Project-URL: Issues, https://github.com/chekos/pypums/issues
Project-URL: CI, https://github.com/chekos/pypums/actions
Project-URL: Changelog, https://github.com/chekos/pypums/releases
Platform: UNKNOWN
Requires-Python: >=3.6
License-File: LICENSE
Requires-Dist: us (>=2.0.2)
Requires-Dist: httpx (>=0.22.0)
Requires-Dist: pandas (>=1.1.0)
Requires-Dist: rich (>=11.0.0)
Requires-Dist: typer (>=0.4.0)
Provides-Extra: docs
Requires-Dist: mkdocs ; extra == 'docs'
Requires-Dist: mdx-include ; extra == 'docs'
Requires-Dist: mkdocstrings ; extra == 'docs'
Requires-Dist: mkdocs-typer ; extra == 'docs'
Requires-Dist: pymdown-extensions ; extra == 'docs'
Provides-Extra: test
Requires-Dist: pytest ; extra == 'test'
